{
  "custom": [
    {
      "label": "",
      "type": "pamSettings",
      "value": [
        {
          "allowSupplyHost": "",
          "connection": {},
          "portForward": {}
        }
      ]
    }
  ],
  "fields": [
    {
      "label": "name-1180",
      "required": true,
      "type": "rbiUrl",
      "value": [
        "http://10.16.9.208:9009"
      ]
    },
    {
      "label": "name-1181",
      "type": "pamRemoteBrowserSettings",
      "value": [
        {
          "connection": {
            "allowUrlManipulation": true,
            "httpCredentialsUid": "h5ocoV5UNNAoFpqof_KcNk",
            "protocol": "http",
            "recordingIncludeKeys": true
          }
        }
      ]
    },
    {
      "label": "name-1148",
      "type": "trafficEncryptionSeed",
      "value": [
        "8DVcgYQsQir9kua93o48QuC17Btggqu6JIZwRdYyNpk="
      ]
    },
    {
      "label": "name-1155",
      "type": "fileRef",
      "value": []
    },
    {
      "label": "name-1156",
      "type": "oneTimeCode",
      "value": []
    }
  ],
  "folders": [
    {
      "path": "/anon/path-N",
      "shared_folder_uid": "N0UvodFBVA3W_PgW3CG9zb"
    }
  ],
  "notes": "",
  "record_uid": "hUwXHyzkF0EL-TcD7F2V5b",
  "shared_folder_permissions": [],
  "title": "name-645",
  "type": "pamRemoteBrowser",
  "user_permissions": []
}