{
  "custom": [],
  "fields": [
    {
      "type": "passkey",
      "value": []
    },
    {
      "type": "login",
      "value": [
        "name-1214"
      ]
    },
    {
      "type": "password",
      "value": [
        "redacted-PLACEHOLDER"
      ]
    },
    {
      "type": "url",
      "value": [
        "https://example.test/path-N"
      ]
    },
    {
      "type": "fileRef",
      "value": []
    },
    {
      "type": "oneTimeCode",
      "value": []
    }
  ],
  "folders": [
    {
      "path": "/anon/path-N",
      "shared_folder_uid": "2JP0F7RQbilqCz50etRJo5"
    }
  ],
  "notes": "",
  "record_uid": "y1U1RB90KfDC1NzJggkTP1",
  "shared_folder_permissions": [],
  "title": "name-840",
  "type": "login",
  "user_permissions": []
}